{
    "associatedOU": "Synectiks",
	"associatedDept":"LOGISTICS",
	"associatedProduct":"DIGITAL AUCTION",
	"associatedEnv":"STAGE",
	"serviceType":"Data",
	"serviceHostingType":"ClusterManaged",
	"serviceNature": "Common",
	"associatedCommonService": "Dataflow",
	"associatedBusinessService": "NA",
    "serviceName":"Dataflow-data1",
    "description": "Dataflow Postgresql DB for App1",
    "clusterServiceLoaction":{
        "landingZone":"567373484",
        "productEnclave":"567373484-VPC1",
        "clusterId":"Cluster1",
        "clusterName":"Non-Prod-Cluster",     
        "clusterNamespace":"DIGITAL AUCTION-DEV",
    "managementUrl":"Url-1"
}
}